microdjango/__init__.py
microdjango-0.0.0.dev0.dist-info/LICENSE
microdjango-0.0.0.dev0.dist-info/WHEEL
microdjango-0.0.0.dev0.dist-info/METADATA
microdjango-0.0.0.dev0.dist-info/RECORD
